odoo/addons/mrp_analytic/README.rst
odoo/addons/mrp_analytic/__init__.py
odoo/addons/mrp_analytic/__manifest__.py
odoo/addons/mrp_analytic/i18n/ca.po
odoo/addons/mrp_analytic/i18n/de.po
odoo/addons/mrp_analytic/i18n/el_GR.po
odoo/addons/mrp_analytic/i18n/es.po
odoo/addons/mrp_analytic/i18n/es_MX.po
odoo/addons/mrp_analytic/i18n/fi.po
odoo/addons/mrp_analytic/i18n/fr.po
odoo/addons/mrp_analytic/i18n/hr.po
odoo/addons/mrp_analytic/i18n/mrp_analytic.pot
odoo/addons/mrp_analytic/i18n/pt_BR.po
odoo/addons/mrp_analytic/i18n/sk_SK.po
odoo/addons/mrp_analytic/i18n/sl.po
odoo/addons/mrp_analytic/i18n/tr.po
odoo/addons/mrp_analytic/i18n/zh_CN.po
odoo/addons/mrp_analytic/models/__init__.py
odoo/addons/mrp_analytic/models/analytic_account.py
odoo/addons/mrp_analytic/models/mrp_production.py
odoo/addons/mrp_analytic/models/stock_move.py
odoo/addons/mrp_analytic/readme/CONTRIBUTORS.rst
odoo/addons/mrp_analytic/readme/DESCRIPTION.rst
odoo/addons/mrp_analytic/readme/HISTORY.rst
odoo/addons/mrp_analytic/readme/USAGE.rst
odoo/addons/mrp_analytic/static/description/icon.png
odoo/addons/mrp_analytic/static/description/icon.svg
odoo/addons/mrp_analytic/static/description/index.html
odoo/addons/mrp_analytic/tests/__init__.py
odoo/addons/mrp_analytic/tests/test_mrp_analytic.py
odoo/addons/mrp_analytic/views/analytic_account_view.xml
odoo/addons/mrp_analytic/views/mrp_view.xml
odoo14_addon_mrp_analytic-14.0.1.1.0.dist-info/METADATA
odoo14_addon_mrp_analytic-14.0.1.1.0.dist-info/WHEEL
odoo14_addon_mrp_analytic-14.0.1.1.0.dist-info/top_level.txt
odoo14_addon_mrp_analytic-14.0.1.1.0.dist-info/RECORD
