Metadata-Version: 2.1
Name: odoo14-addon-mrp-analytic
Version: 14.0.1.1.0
Summary: Adds the analytic account to the production order
Home-page: https://github.com/OCA/account-analytic
Author: ForgeFlow, Antiun Ingeniería, Serv. Tecnol. Avanzados - Pedro M. Baeza, José L. Sandoval A., Open Source Integrators, Odoo Community Association (OCA)
Author-email: support@odoo-community.org
License: AGPL-3
Platform: UNKNOWN
Classifier: Programming Language :: Python
Classifier: Framework :: Odoo
Classifier: License :: OSI Approved :: GNU Affero General Public License v3
Requires-Python: >=3.6
Requires-Dist: odoo (<14.1dev,>=14.0a)
